mosec/__init__.py
mosec/_version.py
mosec/args.py
mosec/coordinator.py
mosec/errors.py
mosec/ipc.py
mosec/protocol.py
mosec/server.py
mosec/worker.py
mosec/bin/mosec
mosec/mixin/__init__.py
mosec/mixin/msgpack_worker.py
mosec/plugins/__init__.py
mosec/plugins/plasma_shm.py
mosec_tiinfer-0.0.7.dist-info/LICENSE
mosec_tiinfer-0.0.7.dist-info/METADATA
mosec_tiinfer-0.0.7.dist-info/WHEEL
mosec_tiinfer-0.0.7.dist-info/top_level.txt
mosec_tiinfer-0.0.7.dist-info/RECORD
