Metadata-Version: 2.1
Name: mosec-tiinfer
Version: 0.0.7
Summary: Model Serving made Efficient in the Cloud.
Home-page: https://github.com/mosecorg/mosec
Author: Keming Yang
Author-email: kemingy94@gmail.com
License: Apache License 2.0
Platform: UNKNOWN
Requires-Python: >=3.6
Provides-Extra: dev
Requires-Dist: setuptools-scm (>=7) ; extra == 'dev'
Requires-Dist: pytest (>=6) ; extra == 'dev'
Requires-Dist: pytest-mock (>=3.5) ; extra == 'dev'
Requires-Dist: mypy (>=0.910) ; extra == 'dev'
Requires-Dist: pylint (>=2.13.8) ; extra == 'dev'
Requires-Dist: pydocstyle (>=6.1.1) ; extra == 'dev'
Requires-Dist: black (>=20.8b1) ; extra == 'dev'
Requires-Dist: isort (>=5.6) ; extra == 'dev'
Requires-Dist: autoflake (>=1.4) ; extra == 'dev'
Requires-Dist: msgpack (>=1.0.2) ; extra == 'dev'
Requires-Dist: pre-commit (>=2.15.0) ; extra == 'dev'
Requires-Dist: requests (~=2.28) ; extra == 'dev'
Requires-Dist: httpx (>=0.21.0) ; extra == 'dev'
Provides-Extra: doc
Requires-Dist: mkdocstrings[python] (>=0.16.0) ; extra == 'doc'
Requires-Dist: mkdocs-material (>=7.3.0) ; extra == 'doc'
Requires-Dist: mkdocs-gen-files (>=0.3.3) ; extra == 'doc'
Provides-Extra: plugin
Requires-Dist: pyarrow (>=0.6.1) ; extra == 'plugin'
Requires-Dist: msgpack (>=1.0.2) ; extra == 'plugin'
